vibrant/__init__.py
vibrant/generator.py
vibrant/image.py
vibrant/main.py
vibrant/models.py
vibrant/utils.py
vibrant_python-0.1.6.dist-info/LICENSE.md
vibrant_python-0.1.6.dist-info/METADATA
vibrant_python-0.1.6.dist-info/WHEEL
vibrant_python-0.1.6.dist-info/RECORD
