Metadata-Version: 2.1
Name: vibrant-python
Version: 0.1.6
Summary: Extract color palettes from images in format similar to palettes module in Android.
License: MIT
Author: totallynotadi
Author-email: g.aditya2048@gmail.com
Requires-Python: >=3.8,<4.0
Classifier: License :: OSI Approved :: MIT License
Classifier: Programming Language :: Python :: 3
Classifier: Programming Language :: Python :: 3.8
Classifier: Programming Language :: Python :: 3.9
Classifier: Programming Language :: Python :: 3.10
Classifier: Programming Language :: Python :: 3.11
Classifier: Programming Language :: Python :: 3.12
Requires-Dist: Pillow (>=10.1.0,<11.0.0)
Requires-Dist: requests (>=2.31.0,<3.0.0)
